prescient_sdk/__init__.py
prescient_sdk/client.py
prescient_sdk/config.py
prescient_sdk/upload.py
prescient_sdk-0.3.0.dist-info/METADATA
prescient_sdk-0.3.0.dist-info/WHEEL
prescient_sdk-0.3.0.dist-info/licenses/LICENSE
prescient_sdk-0.3.0.dist-info/RECORD
