Metadata-Version: 2.4
Name: prescient-sdk
Version: 0.3.0
Summary: A Python SDK for integrating with Prescient services
Project-URL: Homepage, https://sparkgeo.github.io/prescient-sdk/
Project-URL: Repository, https://github.com/sparkgeo/prescient-sdk
Project-URL: Issues, https://github.com/sparkgeo/prescient-sdk/issues
License: MIT License
License-File: LICENSE
Requires-Python: >=3.9
Requires-Dist: boto3>=1.35.19
Requires-Dist: msal>=1.31.0
Requires-Dist: pydantic-settings>=2.5.2
